setup.py
bin/classify
bin/torrent-cleaner
torrenthelper/__init__.py
torrenthelper/actions.py
torrenthelper/classify.py
torrenthelper/fileutil.py
torrenthelper.egg-info/PKG-INFO
torrenthelper.egg-info/SOURCES.txt
torrenthelper.egg-info/dependency_links.txt
torrenthelper.egg-info/top_level.txt