Metadata-Version: 1.0
Name: torrenthelper
Version: 0.5
Summary: Media file classification tools
Home-page: UNKNOWN
Author: Arjan Scherpenisse
Author-email: arjan@scherpenisse.net
License: UNKNOWN
Platform: UNKNOWN
